Workbook

Sheet Instructions
A1: MS Excel Practical Exam
A2: Total Questions: 30
A3: Difficulty Level: Medium
A4: Syllabus: Formulas, Logical Functions, Lookups, INDEX-MATCH, Pivot Tables & Charts, Data Analysis
A5: Attempt all questions using appropriate Excel tools/functions.

Sheet Sales_Data
A1: Order_ID | B1: Region | C1: Salesperson | D1: Product | E1: Quantity | F1: Unit_Price | G1: Sales_Date
A2: 301 | B2: North | C2: Amit | D2: Laptop | E2: 2 | F2: 45000 | G2: 05-01-2025
A3: 302 | B3: South | C3: Riya | D3: Mobile | E3: 5 | F3: 15000 | G3: 07-01-2025
A4: 303 | B4: East | C4: Kunal | D4: Tablet | E4: 3 | F4: 18000 | G4: 10-01-2025
A5: 304 | B5: West | C5: Neha | D5: Laptop | E5: 1 | F5: 45000 | G5: 12-01-2025
A6: 305 | B6: North | C6: Amit | D6: Mobile | E6: 4 | F6: 15000 | G6: 15-01-2025
A7: 306 | B7: South | C7: Riya | D7: Laptop | E7: 2 | F7: 45000 | G7: 18-01-2025

Sheet Product_Master
A1: Product | B1: Category | C1: GST_%
A2: Laptop | B2: Electronics | C2: 18
A3: Mobile | B3: Electronics | C3: 12
A4: Tablet | B4: Electronics | C4: 12

Sheet Student_Marks
A1: Student_ID | B1: Name | C1: Maths | D1: Statistics | E1: Excel | F1: Attendance_%
A2: 1 | B2: Rahul | C2: 78 | D2: 82 | E2: 85 | F2: 92
A3: 2 | B3: Sneha | C3: 88 | D3: 91 | E3: 90 | F3: 96
A4: 3 | B4: Arjun | C4: 65 | D4: 70 | E4: 72 | F4: 85
A5: 4 | B5: Pooja | C5: 92 | D5: 89 | E5: 94 | F5: 98
A6: 5 | B6: Vikas | C6: 55 | D6: 60 | E6: 58 | F6: 80

Sheet Questions
A1: 1. Calculate Total Sales for each order (Quantity × Unit_Price). | J1: 2
A2: 2. Calculate GST Amount using VLOOKUP from Product_Master. | J2: 2
A3: 3. Find Final Amount payable (Total Sales + GST). | J3: 2
A4: 4. Find Grand Total of Final Amount. | J4: 2
A5: 5. Count total number of orders using COUNTA. | J5: 2
A6: 6. Find Region-wise total sales using SUMIF. | J6: 2
A7: 7. Use IF to classify Quantity as High (>3) or Low (<=3). | J7: 2
A8: 8. Find the maximum and minimum Final Amount. | J8: 2
A9: 9. Extract month name from Sales_Date. | J9: 2
A10: 10. Sort Sales_Data by Final Amount (Descending). | J10: 2
A11: 11. Use INDEX-MATCH to fetch Product Category. | J11: 2
A12: 12. Calculate average marks of each student. | J12: 2
... A30: 30. Protect the Student_Marks sheet. | J30: 2
J32: =SUM(J1:J30) -> 60

Sheet AnswerSheet
B2: Answer 1 :
B3: =Sales_Data!E2*Sales_Data!F2 -> 90000
B5: Answer 2 : | C5: Answer 3: | D5: Answer 10: | F5: Answer 24 :
B6: Order_ID | C6: Region | D6: Salesperson | E6: Product | F6: Quantity | G6: Unit_Price | H6: Sales_Date | I6: GST Amount | J6: Final Amount to Pay
B7: 301 | C7: North | D7: Amit | E7: Laptop | F7: 2 | G7: 45000 | H7: 05-01-2025 | I7: =G7*F7*(VLOOKUP(AnswerSheet!E7,Product_Master!A1:C4,3))/100 -> 16200 | J7: =(G7*F7)+I7 -> 106200
B8: 306 | C8: South | D8: Riya | E8: Laptop | F8: 2 | G8: 45000 | H8: 18-01-2025 | I8: =G8*F8*(VLOOKUP(AnswerSheet!E7,Product_Master!A1:C4,3))/100 -> 16200 | J8: =(G8*F8)+I8 -> 106200 | L8: > 60,000
B9: 302 | C9: South | D9: Riya | E9: Mobile | F9: 5 | G9: 15000 | H9: 07-01-2025 | I9: =G9*F9*(VLOOKUP(AnswerSheet!E7,Product_Master!A1:C4,3))/100 -> 13500 | J9: =(G9*F9)+I9 -> 88500
B10: 305 | C10: North | D10: Amit | E10: Mobile | F10: 4 | G10: 15000 | H10: 15-01-2025 | I10: =G10*F10*(VLOOKUP(AnswerSheet!E7,Product_Master!A1:C4,3))/100 -> 10800 | J10: =(G10*F10)+I10 -> 70800
B11: 303 | C11: East | D11: Kunal | E11: Tablet | F11: 3 | G11: 18000 | H11: 10-01-2025 | I11: =G11*F11*(VLOOKUP(AnswerSheet!E7,Product_Master!A1:C4,3))/100 -> 9720 | J11: =(G11*F11)+I11 -> 63720
B12: 304 | C12: West | D12: Neha | E12: Laptop | F12: 1 | G12: 45000 | H12: 12-01-2025 | I12: =G12*F12*(VLOOKUP(AnswerSheet!E7,Product_Master!A1:C4,3))/100 -> 8100 | J12: =(G12*F12)+I12 -> 53100
I13: Answer 4 : | J13: =SUM(J7:J12) -> 488520
B15: Answer 5 :
B16: Total Number of order : | C16: =COUNTA(C7:C12) -> 6
B18: Answer 6 :
B19: North | C19: =SUMIF(C7:C12,C7,AnswerSheet!J7:J12) -> 177000
B20: South | C20: =SUMIF(C7:C12,C8,J7:J12) -> 194700
B21: East | C21: =SUMIF(C7:C12,C9,J7:J12) -> 194700
B22: West | C22: =SUMIF(C7:C12,C10,J7:J12) -> 177000
B24: Answer 7 :
B25: Quantity | C25: >3 or <=3
B26: 2 | C26: =IF(B26>3,"high","low") -> low
B27: 5 | C27: =IF(B27>3,"high","low") -> high
B28: 3 | C28: =IF(B28>3,"high","low") -> low
B29: 1 | C29: =IF(B29>3,"high","low") -> low
B30: 4 | C30: =IF(B30>3,"high","low") -> high
B31: 2 | C31: =IF(B31>3,"high","low") -> low
B33: Answer 8 :
B34: Maximum Final Amount | C34: =MAX(J7:J12) -> 106200
B35: Minimum Final Amount | C35: =MIN(J7:J12) -> 53100
B37: Answer 9 :
B38: Month Name | C38: =TEXT(AnswerSheet!G2,"mmmm") -> January
B40: Answer 10 :
B41: In upper table
B43: Answer 11 :
B44: Index match que - skip
B46: Answer 12 : | C46: Answer 13 : | D46: Answer 15 :
B47: Student_ID | C47: Name | D47: Maths | E47: Statistics | F47: Excel | G47: Attendance_% | H47: Average | I47: Eligiblity | J47: Topper
B48: 1 | C48: Rahul | D48: 78 | E48: 82 | F48: 85 | G48: 92 | H48: =AVERAGE(D48:F48) -> 81.666667 | I48: =IF(G48>85,"Eligible","Not Eligible") -> Eligible
B49: 2 | C49: Sneha | D49: 88 | E49: 91 | F49: 90 | G49: 96 | H49: =AVERAGE(D49:F49) -> 89.666667 | I49: =IF(G49>85,"Eligible","Not Eligible") -> Eligible
B50: 3 | C50: Arjun | D50: 65 | E50: 70 | F50: 72 | G50: 85 | H50: =AVERAGE(D50:F50) -> 69 | I50: =IF(G50>85,"Eligible","Not Eligible") -> Not Eligible
B51: 4 | C51: Pooja | D51: 92 | E51: 89 | F51: 94 | G51: 98 | H51: =AVERAGE(D51:F51) -> 91.666667 | I51: =IF(G51>85,"Eligible","Not Eligible") -> Eligible
B52: 5 | C52: Vikas | D52: 55 | E52: 60 | F52: 58 | G52: 80 | H52: =AVERAGE(D52:F52) -> 57.666667 | I52: =IF(G52>85,"Eligible","Not Eligible") -> Not Eligible
B54: Answer 14 :
B55: Student with 90% or above | C55: =COUNTIF(G48:G52,">90") -> 3
B57: Answer 15 :
B58: Above table
B60: Answer 16 :
B61: Product wise total sales
B62: Row Labels | C62: Sum of Final Amount to Pay
B63: Laptop | C63: 265500
B64: Mobile | C64: 159300
B65: Tablet | C65: 63720
B66: Grand Total | C66: 488520
B68: Answer 17 :
B69: Region wise total sales
B70: Row Labels | C70: Sum of Final Amount to Pay
B71: East | C71: 63720
B72: North | C72: 177000
B73: South | C73: 194700
B74: West | C74: 53100
B75: Grand Total | C75: 488520
B77: Answer 18 :
B93: Answer 19 :
B111: Answer 20 :
B112: =MEDIAN(E48,E49,E50,E51,E52) -> 82
B114: Answer 21 :
B115: =_xlfn.STDEV.S(F48:F52) -> 14.737707
B117: Answer 22 :
B118: Student_ID | C118: Name | D118: Contcat
B119: 1 | C119: Rahul | D119: =_xlfn.CONCAT(B119,C119) -> 1Rahul
B120: 2 | C120: Sneha | D120: =_xlfn.CONCAT(B120,C120) -> 2Sneha
B121: 3 | C121: Arjun | D121: =_xlfn.CONCAT(B121,C121) -> 3Arjun
B122: 4 | C122: Pooja | D122: =_xlfn.CONCAT(B122,C122) -> 4Pooja
B123: 5 | C123: Vikas | D123: =_xlfn.CONCAT(B123,C123) -> 5Vikas
B125: Answer 23 :
B126: Salesperson | C126: first two letter
B127: Amit | C127: =LEFT(B127,2) -> Am
B128: Riya | C128: =LEFT(B128,2) -> Ri
B129: Riya | C129: =LEFT(B129,2) -> Ri
B130: Amit | C130: =LEFT(B130,2) -> Am
B131: Kunal | C131: =LEFT(B131,2) -> Ku
B132: Neha | C132: =LEFT(B132,2) -> Ne
B134: Answer 24 :
B135: Above table
B137: Answer 25 :
B138: Order_ID | C138: Region | D138: Salesperson | E138: Product | F138: Quantity | G138: Unit_Price | H138: Sales_Date
B139: 301 | C139: North | D139: Amit | E139: Laptop | F139: 2 | G139: 45000 | H139: 05-01-2025
B140: 302 | C140: South | D140: Riya | E140: Mobile | F140: 5 | G140: 15000 | H140: 07-01-2025
B141: 303 | C141: East | D141: Kunal | E141: Tablet | F141: 3 | G141: 18000 | H141: 10-01-2025
B142: 304 | C142: West | D142: Neha | E142: Laptop | F142: 1 | G142: 45000 | H142: 12-01-2025
B143: 305 | C143: North | D143: Amit | E143: Mobile | F143: 4 | G143: 15000 | H143: 15-01-2025
B144: 306 | C144: South | D144: Riya | E144: Laptop | F144: 2 | G144: 45000 | H144: 18-01-2025
B147: Answer 26 :
B148: Laptop order in north region | C148: =COUNTIFS(Sales_Data!B2:B7,Sales_Data!B2,Sales_Data!D2:D7,Sales_Data!D2) -> 1
B150: Answer 27 : | C150: Already Rounded!!!!!
B151: 45000 | C151: =ROUND(B151,-3) -> 45000
B152: 15000 | C152: =ROUND(B152,-3) -> 15000
B153: 18000 | C153: =ROUND(B153,-3) -> 18000
B154: 45000 | C154: =ROUND(B154,-3) -> 45000
B155: 15000 | C155: =ROUND(B155,-3) -> 15000
...
